graphx/__init__.py
graphx/graph.py
graphx/graphx.py
graphx/pipe.py
graphx/query.py
graphx/utils.py
graphx/vertex.py
tests/__init__.py
tests/dummy.py
tests/test_graph.py
tests/test_graphx.py
tests/test_pipe.py
tests/test_query.py
tests/test_vertex.py
linnngraphx-0.3.dist-info/LICENSE
linnngraphx-0.3.dist-info/METADATA
linnngraphx-0.3.dist-info/WHEEL
linnngraphx-0.3.dist-info/top_level.txt
linnngraphx-0.3.dist-info/RECORD
