Metadata-Version: 2.1
Name: linnngraphx
Version: 0.3
Summary: GraphX is a Python-based in-memory graph storage engine designed to facilitate the representation of complex relational queries, enabling users to store data while effectively capturing relationships between individual data points.
Home-page: UNKNOWN
License: UNKNOWN
Platform: UNKNOWN
License-File: LICENSE
